SiEPIC_TestCreator/__init__.py
SiEPIC_TestCreator/__main__.py
SiEPIC_TestCreator/config.py
SiEPIC_TestCreator/run_gui_for_debugging.py
SiEPIC_TestCreator/sequencecreator.py
SiEPIC_TestCreator/sequencecreatorvariables.py
SiEPIC_TestCreator/sequencetracker.py
SiEPIC_TestCreator/yamlcheck.py
SiEPIC_TestCreator/sequences/__init__.py
SiEPIC_TestCreator/sequences/BIO/__init__.py
SiEPIC_TestCreator/sequences/DREAM/__init__.py
SiEPIC_TestCreator/sequences/DREAM/current_sweep.py
SiEPIC_TestCreator/sequences/DREAM/set_current_wavelength_sweep.py
SiEPIC_TestCreator/sequences/DREAM/set_voltage_wavelength_sweep.py
SiEPIC_TestCreator/sequences/DREAM/set_wavelength_current_sweep.py
SiEPIC_TestCreator/sequences/DREAM/set_wavelength_voltage_sweep.py
SiEPIC_TestCreator/sequences/DREAM/voltage_sweep.py
SiEPIC_TestCreator/sequences/DREAM/wavelength_sweep.py
SiEPIC_TestCreator/sequences/IDA/__init__.py
SiEPIC_TestCreator/sequences/IDA/current_sweep_ida.py
SiEPIC_TestCreator/sequences/IDA/set_current_wavelength_sweep_ida.py
SiEPIC_TestCreator/sequences/IDA/set_voltage_wavelength_sweep_ida.py
SiEPIC_TestCreator/sequences/IDA/set_wavelength_current_sweep_ida.py
SiEPIC_TestCreator/sequences/IDA/set_wavelength_voltage_sweep_ida.py
SiEPIC_TestCreator/sequences/IDA/voltage_sweep_ida.py
SiEPIC_TestCreator/sequences/IDA/wavelength_sweep_ida.py
SiEPIC_TestCreator/sequences/core/__init__.py
SiEPIC_TestCreator/sequences/core/laser_sweep.py
SiEPIC_TestCreator/sequences/core/results.py
SiEPIC_TestCreator/sequences/core/sequence.py
SiEPIC_TestCreator/sequences/core/smu_sweep.py
SiEPIC_TestCreator/sequences/template/__init__.py
SiEPIC_TestCreator-0.1.21.dist-info/LICENSE
SiEPIC_TestCreator-0.1.21.dist-info/METADATA
SiEPIC_TestCreator-0.1.21.dist-info/WHEEL
SiEPIC_TestCreator-0.1.21.dist-info/entry_points.txt
SiEPIC_TestCreator-0.1.21.dist-info/top_level.txt
SiEPIC_TestCreator-0.1.21.dist-info/RECORD
